curvepy/__init__.py
curvepy/accumulator.py
curvepy/accumulator_map.py
curvepy/aggregate.py
curvepy/const.py
curvepy/constant.py
curvepy/curve.py
curvepy/ema.py
curvepy/empty.py
curvepy/extension/__init__.py
curvepy/extension/constant.py
curvepy/extension/extension.py
curvepy/extension/sin.py
curvepy/extension/tangent.py
curvepy/extremas.py
curvepy/generic.py
curvepy/integral.py
curvepy/line.py
curvepy/map.py
curvepy/offset.py
curvepy/piecewise.py
curvepy/points.py
curvepy/quotes.py
curvepy/scan.py
curvepy/sin.py
curvepy/sma.py
curvepy/trend.py
curvepy/util.py
curvepy-0.2.0.dist-info/entry_points.txt
curvepy-0.2.0.dist-info/LICENSE
curvepy-0.2.0.dist-info/WHEEL
curvepy-0.2.0.dist-info/METADATA
curvepy-0.2.0.dist-info/RECORD
