Metadata-Version: 2.1
Name: curvepy
Version: 0.2.0
Summary: A mathematical and financial function curve utility library.
Home-page: https://github.com/diatche/func
License: MIT
Keywords: curve,func,function,sma
Author: Pavel Diatchenko
Author-email: diatche@gmail.com
Requires-Python: >=3.5,<4
Classifier: License :: OSI Approved :: MIT License
Classifier: Programming Language :: Python :: 3
Classifier: Programming Language :: Python :: 3.5
Classifier: Programming Language :: Python :: 3.6
Classifier: Programming Language :: Python :: 3.7
Classifier: Programming Language :: Python :: 3.8
Classifier: Programming Language :: Python :: 3.9
Requires-Dist: arrow (>=0.12.1,<0.13.0)
Requires-Dist: intervalpy (>=0.1.0,<0.2.0)
Requires-Dist: numpy (>=1.15.0,<2.0.0)
Requires-Dist: pyduration (>=0.1.0,<0.2.0)
Project-URL: Repository, https://github.com/diatche/func
